pymongosl/__init__.py
pymongosl/connection.py
pymongosl/cursor.py
pymongosl/dialect.py
pymongosl/encoding.py
pymongosl/errors.py
pymongosl/log.py
pymongosl/proxy.py
pymongosl/types.py
pymongosl-1.0.0.dist-info/DESCRIPTION.rst
pymongosl-1.0.0.dist-info/METADATA
pymongosl-1.0.0.dist-info/RECORD
pymongosl-1.0.0.dist-info/WHEEL
pymongosl-1.0.0.dist-info/entry_points.txt
pymongosl-1.0.0.dist-info/metadata.json
pymongosl-1.0.0.dist-info/top_level.txt
