Metadata-Version: 2.0
Name: pymongosl
Version: 1.0.0
Summary: MongoDB DBAPI Driver
Home-page: UNKNOWN
Author: YangSheBing
Author-email: 811068990@qq.com
License: UNKNOWN
Keywords: MongoDB SQLAlchemy
Platform: UNKNOWN
Classifier: Development Status :: 3 - Alpha
Classifier: Environment :: Console
Classifier: Intended Audience :: Developers
Classifier: Programming Language :: Python
Classifier: Programming Language :: Python :: 2.7
Classifier: Programming Language :: Python :: Implementation :: CPython
Classifier: Programming Language :: Python :: Implementation :: PyPy
Classifier: Topic :: Database :: Front-Ends
Requires-Dist: python-dateutil (==2.4.2)
Requires-Dist: requests (==2.8.1)
